fusion/__init__.py
fusion/attributes.py
fusion/authentication.py
fusion/credentials.py
fusion/dataflow.py
fusion/dataset.py
fusion/exceptions.py
fusion/fusion.py
fusion/fusion_filesystem.py
fusion/fusion_types.py
fusion/product.py
fusion/report.py
fusion/report_attributes.py
fusion/types.py
fusion/utils.py
pyfusion37-2.0.0.dist-info/LICENSE
pyfusion37-2.0.0.dist-info/METADATA
pyfusion37-2.0.0.dist-info/WHEEL
pyfusion37-2.0.0.dist-info/RECORD
