Metadata-Version: 2.1
Name: pyfusion37
Version: 2.0.0
Summary: JPMC Fusion Developer Tools
Home-page: https://github.com/jpmorganchase/fusion-3.7
License: Apache-2.0
Author: FusionDevs
Author-email: fusion_developers@jpmorgan.com
Requires-Python: >=3.7.1,<3.8
Classifier: Development Status :: 5 - Production/Stable
Classifier: Intended Audience :: Developers
Classifier: License :: OSI Approved :: Apache Software License
Classifier: Natural Language :: English
Classifier: Programming Language :: Python :: 3
Classifier: Programming Language :: Python :: 3.7
Classifier: Typing :: Typed
Requires-Dist: aiohttp (<=3.7.4)
Requires-Dist: certifi (<=2018.11.8)
Requires-Dist: cryptography (<=3.1.0)
Requires-Dist: fsspec (<2023.1.0)
Requires-Dist: joblib (<=1.2.0)
Requires-Dist: pandas (<=0.24.2)
Requires-Dist: pyarrow (>=0.17.0,<0.18.0)
Requires-Dist: pyjwt (<=1.5.3)
Requires-Dist: pytz
Requires-Dist: requests (<=2.24.0)
Requires-Dist: tabulate (<=0.7.7)
Requires-Dist: tqdm (<=4.48.0)
Requires-Dist: typing-extensions (>=3.10,<4.0)
Requires-Dist: urllib3 (==1.26.6)
